fedora_elections_messages/__init__.py
fedora_elections_messages/base.py
fedora_elections_messages/candidate_delete.py
fedora_elections_messages/candidate_edit.py
fedora_elections_messages/candidate_new.py
fedora_elections_messages/election_edit.py
fedora_elections_messages/election_new.py
fedora_elections_messages-1.0.1.dist-info/LICENSE
fedora_elections_messages-1.0.1.dist-info/METADATA
fedora_elections_messages-1.0.1.dist-info/WHEEL
fedora_elections_messages-1.0.1.dist-info/entry_points.txt
fedora_elections_messages-1.0.1.dist-info/top_level.txt
fedora_elections_messages-1.0.1.dist-info/RECORD
